[
  {
    "processor_name": "bottom_center_info_watermark",
    "location_text": "{{ custom_text|default('') }}",
    "time_text": "{{ format_photo_time(exif) }}",
    "focal_text": "{{ format_focal_length(exif) }}",
    "shutter_text": "{{ format_shutter_speed(exif) }}",
    "aperture_text": "{{ format_aperture(exif) }}",
    "iso_text": "{{ format_iso(exif) }}",
    "font_path": "{{ watermark_font|default('AlibabaPuHuiTi-2-45-Light.otf') }}",
    "location_font_path": "{{ watermark_font|default('AlibabaPuHuiTi-2-45-Light.otf') }}",
    "parameter_font_path": "{{ watermark_font|default('AlibabaPuHuiTi-2-45-Light.otf') }}",
    "blend_mode": "screen",
    "color": "(255,255,255,255)",
    "time_color": "(255,255,255,255)",
    "parameter_color": "(255,255,255,255)",
    "location_opacity": 230,
    "time_opacity": 115,
    "parameter_opacity": 165,
    "location_height": "{{vh(4.8)}}",
    "time_height": "{{vh(1.68)}}",
    "parameter_height": "{{vh(2.4)}}",
    "line_spacing": "{{vh(0.65)}}",
    "bottom_offset": "{{vh(4.6)}}",
    "parameter_gap": "{{vw(8.8)}}"
  }
]
